paralexe/__init__.py
paralexe/executor.py
paralexe/manager.py
paralexe/rsubprocess.py
paralexe/scheduler.py
paralexe/worker.py
Paralexe-0.1.4.dist-info/METADATA
Paralexe-0.1.4.dist-info/WHEEL
Paralexe-0.1.4.dist-info/top_level.txt
Paralexe-0.1.4.dist-info/RECORD
