Metadata-Version: 2.1
Name: Paralexe
Version: 0.1.4
Summary: Parallel Execution
Home-page: https://github.com/dvm-shlee/paralexe
Author: SungHo Lee
Author-email: shlee@unc.edu
License: GNLv3
Keywords: Parallel Execution
Platform: UNKNOWN
Classifier: Development Status :: 5 - Production/Stable
Classifier: Framework :: Jupyter
Classifier: Intended Audience :: Science/Research
Classifier: Topic :: Scientific/Engineering :: Information Analysis
Classifier: Natural Language :: English
Classifier: Programming Language :: Python :: 2.7
Classifier: Programming Language :: Python :: 3.7
Requires-Dist: tqdm
Requires-Dist: psutil (>=5.7.0)
Requires-Dist: shleeh (>=0.0.4)
